reserver/__init__.py
reserver/__main__.py
reserver/errors.py
reserver/functions.py
reserver/params.py
reserver/uploader.py
reserver/utils.py
reserver-0.6.dist-info/licenses/AUTHORS.md
reserver-0.6.dist-info/licenses/LICENSE
reserver-0.6.dist-info/METADATA
reserver-0.6.dist-info/WHEEL
reserver-0.6.dist-info/entry_points.txt
reserver-0.6.dist-info/top_level.txt
reserver-0.6.dist-info/RECORD
