Metadata-Version: 2.4
Name: reserver
Version: 0.6
Summary: PyPI package name reserver
Home-page: https://github.com/openscilab/reserver
Download-URL: https://github.com/openscilab/reserver/tarball/v0.6
Author: Reserver Development Team
Author-email: reserver@openscilab.com
License: MIT
Project-URL: Source, https://github.com/openscilab/reserver
Keywords: pypi pip package name reserve reserver reservation python
Classifier: Development Status :: 3 - Alpha
Classifier: Intended Audience :: Developers
Classifier: Natural Language :: English
Classifier: License :: OSI Approved :: MIT License
Classifier: Operating System :: OS Independent
Classifier: Programming Language :: Python :: 3.7
Classifier: Programming Language :: Python :: 3.8
Classifier: Programming Language :: Python :: 3.9
Classifier: Programming Language :: Python :: 3.10
Classifier: Programming Language :: Python :: 3.11
Classifier: Programming Language :: Python :: 3.12
Classifier: Programming Language :: Python :: 3.13
Classifier: Intended Audience :: Developers
Classifier: Intended Audience :: Education
Classifier: Intended Audience :: End Users/Desktop
Classifier: Intended Audience :: Manufacturing
Classifier: Intended Audience :: Science/Research
Requires-Python: >=3.7
License-File: LICENSE
License-File: AUTHORS.md
Requires-Dist: art>=5.3
Requires-Dist: setuptools>=40.8.0
Requires-Dist: wheel>=0.35.0
Requires-Dist: twine>=3.5.0
Requires-Dist: chardet>=4.0.0
Requires-Dist: build>=0.9.0
Dynamic: author
Dynamic: author-email
Dynamic: classifier
Dynamic: description
Dynamic: description-content-type
Dynamic: download-url
Dynamic: home-page
Dynamic: keywords
Dynamic: license
Dynamic: license-file
Dynamic: project-url
Dynamic: requires-dist
Dynamic: requires-python
Dynamic: summary
